pyaterochka_api/__init__.py
pyaterochka_api/enums.py
pyaterochka_api/manager.py
pyaterochka_api/endpoints/advertising.py
pyaterochka_api/endpoints/catalog.py
pyaterochka_api/endpoints/general.py
pyaterochka_api/endpoints/geolocation.py
pyaterochka_api-0.2.2.dist-info/licenses/LICENSE
pyaterochka_api-0.2.2.dist-info/METADATA
pyaterochka_api-0.2.2.dist-info/WHEEL
pyaterochka_api-0.2.2.dist-info/top_level.txt
pyaterochka_api-0.2.2.dist-info/RECORD
