Metadata-Version: 2.4
Name: pyaterochka_api
Version: 0.2.2
Summary: A Python API client for Pyaterochka store catalog
Author: Miskler
License-Expression: MIT
Project-URL: Homepage, https://github.com/Open-Inflation/pyaterochka_api
Project-URL: Repository, https://github.com/Open-Inflation/pyaterochka_api
Project-URL: Documentation, https://open-inflation.github.io/pyaterochka_api/
Keywords: api,pyaterochka,store,catalog
Classifier: Programming Language :: Python :: 3
Classifier: Programming Language :: Python :: 3.10
Classifier: Programming Language :: Python :: 3.11
Classifier: Programming Language :: Python :: 3.12
Classifier: Programming Language :: Python :: 3.13
Classifier: Operating System :: Microsoft :: Windows
Classifier: Operating System :: POSIX :: Linux
Classifier: Intended Audience :: Developers
Classifier: Intended Audience :: Information Technology
Classifier: Topic :: Software Development :: Libraries :: Python Modules
Classifier: Topic :: Internet
Classifier: Topic :: Utilities
Requires-Python: >=3.10
License-File: LICENSE
Requires-Dist: camoufox[geoip]
Requires-Dist: human_requests
Requires-Dist: aiohttp
Requires-Dist: aiohttp-retry
Provides-Extra: tests
Requires-Dist: pytest; extra == "tests"
Requires-Dist: pytest-asyncio; extra == "tests"
Requires-Dist: pytest-typed-schema-shot; extra == "tests"
Requires-Dist: jsoncrack-for-sphinx; extra == "tests"
Dynamic: license-file
